cowsay/__init__.py
cowsay/cows.py
cowsay/modules.py
cowsay/lib/balloon.py
cowsay/lib/faces.py
cowsay/lib/cows/C3PO.py
cowsay/lib/cows/R2_D2.py
cowsay/lib/cows/USA.py
cowsay/lib/cows/ackbar.py
cowsay/lib/cows/aperture.py
cowsay/lib/cows/aperture_blank.py
cowsay/lib/cows/armadillo.py
cowsay/lib/cows/atat.py
cowsay/lib/cows/atom.py
cowsay/lib/cows/awesome_face.py
cowsay/lib/cows/banana.py
cowsay/lib/cows/bearface.py
cowsay/lib/cows/beavis_zen.py
cowsay/lib/cows/bees.py
cowsay/lib/cows/bill_the_cat.py
cowsay/lib/cows/biohazard.py
cowsay/lib/cows/bishop.py
cowsay/lib/cows/black_mesa.py
cowsay/lib/cows/bong.py
cowsay/lib/cows/box.py
cowsay/lib/cows/broken_heart.py
cowsay/lib/cows/bud_frogs.py
cowsay/lib/cows/bunny.py
cowsay/lib/cows/cake.py
cowsay/lib/cows/cake_with_candles.py
cowsay/lib/cows/cat.py
cowsay/lib/cows/cat2.py
cowsay/lib/cows/catfence.py
cowsay/lib/cows/charizardvice.py
cowsay/lib/cows/charlie.py
cowsay/lib/cows/cheese.py
cowsay/lib/cows/chessmen.py
cowsay/lib/cows/chito.py
cowsay/lib/cows/claw_arm.py
cowsay/lib/cows/clippy.py
cowsay/lib/cows/companion_cube.py
cowsay/lib/cows/cower.py
cowsay/lib/cows/cowfee.py
cowsay/lib/cows/cthulhu_mini.py
cowsay/lib/cows/cube.py
cowsay/lib/cows/daemon.py
cowsay/lib/cows/dalek.py
cowsay/lib/cows/dalek_shooting.py
cowsay/lib/cows/default.py
cowsay/lib/cows/docker_whale.py
cowsay/lib/cows/doge.py
cowsay/lib/cows/dolphin.py
cowsay/lib/cows/dragon.py
cowsay/lib/cows/dragon_and_cow.py
cowsay/lib/cows/ebi_furai.py
cowsay/lib/cows/elephant.py
cowsay/lib/cows/elephant2.py
cowsay/lib/cows/elephant_in_snake.py
cowsay/lib/cows/explosion.py
cowsay/lib/cows/eyes.py
cowsay/lib/cows/fat_banana.py
cowsay/lib/cows/fat_cow.py
cowsay/lib/cows/fence.py
cowsay/lib/cows/fire.py
cowsay/lib/cows/flaming_sheep.py
cowsay/lib/cows/fox.py
cowsay/lib/cows/ghost.py
cowsay/lib/cows/ghostbusters.py
cowsay/lib/cows/glados.py
cowsay/lib/cows/goat.py
cowsay/lib/cows/goat2.py
cowsay/lib/cows/golden_eagle.py
cowsay/lib/cows/hand.py
cowsay_py-0.1.2.dist-info/LICENSE
cowsay_py-0.1.2.dist-info/METADATA
cowsay_py-0.1.2.dist-info/WHEEL
cowsay_py-0.1.2.dist-info/top_level.txt
cowsay_py-0.1.2.dist-info/RECORD
