Metadata-Version: 2.1
Name: cowsay-py
Version: 0.1.2
Summary: Python module for cowsay
Home-page: https://github.com/ovlic/cowsay_py
Author: Ovlic
License: MIT
Project-URL: Bug Tracker, https://github.com/ovlic/cowsay_py/issues
Platform: UNKNOWN
Classifier: Operating System :: OS Independent
Classifier: Programming Language :: Python :: 3
Classifier: License :: OSI Approved :: MIT License
Requires-Python: >=3.6
License-File: LICENSE
